{"vtc": "Adyar", "co": "D/O,J L Raveendran", "gender": "FEMALE", "uid": "754646575254", "dist": "Chennai", "state": "Tamil Nadu", "yob": "1996", "loc": "Indira Nagar", "inc": "123", "lm": "T T K Hospital", "mobile": "456", "name": "Priyadarshini J R", "pc": "600020", "po": "Adyar"}
{"loc": "Indira Nagar", "co": "D/O,J L Raveendran", "gender": "FEMALE", "dist": "Chennai", "state": "Tamil Nadu", "vtc": "Adyar", "name": "Priyadarshini J R", "po": "Adyar", "uid": "754646575254", "inc": "100000", "lm": "T T K Hospital", "yob": "1996", "mobile": "9567896742", "pc": "600020"}
